README.md
setup.py
qcloud_python_test.egg-info/PKG-INFO
qcloud_python_test.egg-info/SOURCES.txt
qcloud_python_test.egg-info/dependency_links.txt
qcloud_python_test.egg-info/top_level.txt
utils/__init__.py
utils/test.py