Metadata-Version: 1.0
Name: qcloud-python-test
Version: 0.0.1
Summary: this is test for python on pypi
Home-page: https://github.com/tencentyun/qcloud-cos-sts-sdk
Author: qcloudterminal
Author-email: qcloudterminal@gmail.com
License: MIT
Platform: UNKNOWN
